{
    "genres": {
        "http://id.loc.gov/vocabulary/marcgt/bib": "bibliography",
        "http://id.loc.gov/vocabulary/marcgt/gov": "government publication",
        "http://id.loc.gov/vocabulary/marcgt/fic": "fiction",
        "http://id.loc.gov/vocabulary/marcgt/bio": "biography",
        "http://id.loc.gov/vocabulary/marcgt/sta": "statistics",
        "http://id.loc.gov/vocabulary/marcgt/cpb": "conference publication",
        "http://id.loc.gov/vocabulary/marcgt/cat": "catalog",
        "http://id.loc.gov/vocabulary/marcgt/aut": "autobiography",
        "http://id.loc.gov/vocabulary/marcgt/dir": "directory",
        "http://id.loc.gov/vocabulary/marcgt/dic": "dictionary",
        "http://id.loc.gov/vocabulary/marcgt/leg": "legislation",
        "http://id.loc.gov/vocabulary/marcgt/law": "law report or digest",
        "http://id.loc.gov/vocabulary/marcgt/rev": "review",
        "http://id.loc.gov/vocabulary/marcgt/ind": "index",
        "http://id.loc.gov/vocabulary/marcgt/abs": "abstract or summary",
        "http://id.loc.gov/vocabulary/marcgt/han": "handbook",
        "http://id.loc.gov/vocabulary/marcgt/fes": "festschrift",
        "http://id.loc.gov/vocabulary/marcgt/enc": "encyclopedia",
        "http://id.loc.gov/vocabulary/marcgt/yea": "yearbook",
        "http://id.loc.gov/vocabulary/marcgt/ter": "technical report",
        "http://id.loc.gov/vocabulary/marcgt/the": "thesis",
        "http://id.loc.gov/vocabulary/marcgt/lea": "legal article",
        "http://id.loc.gov/vocabulary/marcgt/lec": "legal case and case notes",
        "http://id.loc.gov/vocabulary/marcgt/sur": "survey of literature",
        "http://id.loc.gov/vocabulary/marcmuscomp/sg": "Songs",
        "http://id.loc.gov/vocabulary/marcgt/dis": "discography",
        "http://id.loc.gov/vocabulary/marcmuscomp/co": "Concertos",
        "http://id.loc.gov/vocabulary/marcmuscomp/sn": "Sonatas",
        "http://id.loc.gov/vocabulary/marcgt/fil": "filmography",
        "http://id.loc.gov/vocabulary/marcmuscomp/sy": "Symphonies",
        "http://id.loc.gov/vocabulary/marcmuscomp/ms": "Masses",
        "http://id.loc.gov/vocabulary/marcmuscomp/op": "Operas",
        "http://id.loc.gov/vocabulary/marcmuscomp/zz": "Other",
        "http://id.loc.gov/vocabulary/marcmuscomp/df": "Dance forms",
        "http://id.loc.gov/vocabulary/marcmuscomp/vr": "Variations",
        "http://id.loc.gov/vocabulary/marcmuscomp/fg": "Fugues",
        "http://id.loc.gov/vocabulary/marcmuscomp/ct": "Cantatas",
        "http://id.loc.gov/vocabulary/marcmuscomp/mo": "Motets",
        "http://id.loc.gov/vocabulary/marcmuscomp/ft": "Fantasias",
        "http://id.loc.gov/vocabulary/marcmuscomp/or": "Oratorios",
        "http://id.loc.gov/vocabulary/marcmuscomp/su": "Suites",
        "http://id.loc.gov/vocabulary/marcmuscomp/pr": "Preludes",
        "http://id.loc.gov/vocabulary/marcmuscomp/ov": "Overtures",
        "http://id.loc.gov/vocabulary/marcgt/tre": "treaty",
        "http://id.loc.gov/vocabulary/marcmuscomp/mr": "Marches",
        "http://id.loc.gov/vocabulary/marcgt/pro": "programmed text",
        "http://id.loc.gov/vocabulary/marcmuscomp/dv": "Divertimentos, serenades, cassations, divertissements, and notturni",
        "http://id.loc.gov/vocabulary/marcmuscomp/rd": "Rondos",
        "https://id.nlm.nih.gov/mesh/D020492": "Periodical (MeSH)",
        "http://id.loc.gov/authorities/genreForms/gf2014026139.": "Periodical (LCGFT)",
        "http://id.loc.gov/vocabulary/marcmuscomp/rq": "Requiems",
        "http://id.loc.gov/vocabulary/marcmuscomp/cn": "Canons and rounds",
        "http://id.loc.gov/vocabulary/marcmuscomp/bt": "Ballets",
        "http://id.loc.gov/vocabulary/marcmuscomp/wz": "Waltzes",
        "http://id.loc.gov/vocabulary/marcmuscomp/fm": "Folk music",
        "http://id.loc.gov/vocabulary/marcmuscomp/md": "Madrigals",
        "http://id.loc.gov/vocabulary/marcgt/map": "map",
        "http://id.loc.gov/vocabulary/marcmuscomp/nc": "Nocturnes",
        "http://id.loc.gov/vocabulary/marcmuscomp/pt": "Part-songs",
        "http://id.loc.gov/vocabulary/marcmuscomp/hy": "Hymns",
        "http://id.loc.gov/vocabulary/marcmuscomp/pm": "Passion music",
        "http://id.loc.gov/vocabulary/marcgt/atl": "atlas",
        "http://id.loc.gov/vocabulary/marcmuscomp/mi": "Minuets",
        "http://id.loc.gov/vocabulary/marcmuscomp/tc": "Toccatas",
        "https://id.nlm.nih.gov/mesh/D020504": "Abstracts (MeSH)",
        "http://id.loc.gov/vocabulary/marcgt/stp": "standard or specification",
        "http://id.loc.gov/vocabulary/marcmuscomp/ts": "Trio-sonatas",
        "http://id.loc.gov/authorities/genreForms/gf2011026723": "Video recordings",
        "http://id.loc.gov/vocabulary/marcmuscomp/ch": "Chorales",
        "http://id.loc.gov/vocabulary/marcmuscomp/st": "Studies and exercises",
        "http://id.loc.gov/vocabulary/marcgt/com": "computer program",
        "http://id.loc.gov/vocabulary/marcmuscomp/cg": "Concerti grossi",
        "http://id.loc.gov/vocabulary/marcmuscomp/cp": "Chansons, polyphonic",
        "http://id.loc.gov/vocabulary/marcmuscomp/an": "Anthems",
        "http://id.loc.gov/vocabulary/marcmuscomp/po": "Polonaises",
        "http://id.loc.gov/vocabulary/marcmuscomp/cl": "Chorale preludes",
        "http://id.loc.gov/vocabulary/marcgt/vid": "videorecording",
        "http://id.loc.gov/authorities/genreForms/gf2014026909": "Librettos",
        "http://id.loc.gov/vocabulary/marcmuscomp/mz": "Mazurkas",
        "http://id.loc.gov/vocabulary/marcmuscomp/cc": "Chant, Christian",
        "http://id.loc.gov/vocabulary/marcmuscomp/ps": "Passacaglias",
        "http://id.loc.gov/vocabulary/marcgt/cgn": "comic or graphic novel",
        "http://id.loc.gov/vocabulary/marcmuscomp/sp": "Symphonic poems",
        "http://id.loc.gov/vocabulary/marcgt/num": "numeric data",
        "http://id.loc.gov/vocabulary/marcmuscomp/pp": "Popular music",
        "http://id.loc.gov/authorities/genreForms/gf2014026110.": "Humor",
        "http://id.loc.gov/vocabulary/marcmuscomp/cz": "Canzonas",
        "http://id.worldcat.org/fast/fst01411641": "Periodicals (FAST)",
        "http://id.loc.gov/vocabulary/marcmuscomp/pv": "Pavans"
    },
    "languages": {
        "eng": "English",
        "ger": "German",
        "fre": "French",
        "spa": "Spanish",
        "rus": "Russian",
        "chi": "Chinese",
        "jpn": "Japanese",
        "ita": "Italian",
        "por": "Portuguese",
        "lat": "Latin",
        "ara": "Arabic",
        "und": "Undetermined",
        "dut": "Dutch",
        "pol": "Polish",
        "swe": "Swedish",
        "heb": "Hebrew",
        "dan": "Danish",
        "kor": "Korean",
        "cze": "Czech",
        "hin": "Hindi",
        "ind": "Indonesian",
        "hun": "Hungarian",
        "mul": "Multiple languages",
        "nor": "Norwegian",
        "tur": "Turkish",
        "scr": "Croatian",
        "zxx": "No linguistic content",
        "urd": "Urdu",
        "tha": "Thai",
        "gre": "Greek, Modern (1453-)",
        "per": "Persian",
        "grc": "Greek, Ancient (to 1453)",
        "san": "Sanskrit",
        "tam": "Tamil",
        "ukr": "Ukrainian",
        "bul": "Bulgarian",
        "scc": "Serbian",
        "rum": "Romanian",
        "ben": "Bengali",
        "vie": "Vietnamese",
        "fin": "Finnish",
        "arm": "Armenian",
        "cat": "Catalan",
        "slo": "Slovak",
        "slv": "Slovenian",
        "yid": "Yiddish",
        "mar": "Marathi",
        "may": "Malay",
        "pan": "Panjabi",
        "afr": "Afrikaans",
        "tel": "Telugu",
        "ota": "Turkish, Ottoman",
        "tib": "Tibetan",
        "ice": "Icelandic",
        "mal": "Malayalam",
        "est": "Estonian",
        "bel": "Belarusian",
        "lit": "Lithuanian",
        "mac": "Macedonian",
        "lav": "Latvian",
        "nep": "Nepali",
        "uzb": "Uzbek",
        "wel": "Welsh",
        "kan": "Kannada",
        "geo": "Georgian",
        "guj": "Gujarati",
        "snh": "Sinhalese",
        "srp": "Serbian",
        "hrv": "Croatian (Discontinued Code)",
        "bur": "Burmese",
        "pli": "Pali",
        "kaz": "Kazakh",
        "tgl": "Tagalog",
        "aze": "Azerbaijani",
        "mon": "Mongolian",
        "jav": "Javanese",
        "iri": "Irish (Discontinued Code)",
        "hau": "Hausa",
        "fro": "French, Old (ca. 842-1300)",
        "swa": "Swahili",
        "map": "Austronesian (Other)",
        "gmh": "German, Middle High (ca. 1050-1500)",
        "syr": "Syriac, Modern",
        "raj": "Rajasthani",
        "ori": "Oriya",
        "alb": "Albanian",
        "sla": "Slavic (Other)",
        "enm": "English, Middle (1100-1500)",
        "arc": "Aramaic",
        "pra": "Prakrit languages",
        "sin": "Sinhalese",
        "chu": "Church Slavic",
        "ang": "English, Old (ca. 450-1100)",
        "gle": "Irish",
        "nic": "Niger-Kordofanian (Other)",
        "kir": "Kyrgyz",
        "frm": "French, Middle (ca. 1300-1600)",
        "tut": "Altaic (Other)",
        "roa": "Romance (Other)",
        "tag": "Tagalog (Discontinued Code)",
        "inc": "Indic (Other)",
        "tat": "Tatar",
        "myn": "Mayan languages",
        "tuk": "Turkmen",
        "sun": "Sundanese",
        "baq": "Basque",
        "sai": "South American Indian (Other)",
        "mai": "Maithili",
        "egy": "Egyptian",
        "akk": "Akkadian",
        "sit": "Sino-Tibetan (Other)",
        "que": "Quechua",
        "pro": "Provençal (to 1500)",
        "cop": "Coptic",
        "int": "Interlingua (International Auxiliary Language Association) (Discontinued Code)",
        "yor": "Yoruba",
        "paa": "Papuan (Other)",
        "bra": "Braj",
        "new": "Newari",
        "pus": "Pushto",
        "amh": "Amharic",
        "bos": "Bosnian",
        "rom": "Romani",
        "gem": "Germanic (Other)",
        "fiu": "Finno-Ugrian (Other)",
        "mol": "Moldavian (Discontinued Code)",
        "roh": "Raeto-Romance",
        "fri": "Frisian (Discontinued Code)",
        "lao": "Lao",
        "snd": "Sindhi",
        "wen": "Sorbian (Other)",
        "nah": "Nahuatl",
        "bak": "Bashkir",
        "pal": "Pahlavi",
        "asm": "Assamese",
        "glg": "Galician",
        "cai": "Central American Indian (Other)",
        "gag": "Galician (Discontinued Code)",
        "uig": "Uighur",
        "tgk": "Tajik",
        "gae": "Scottish Gaelix (Discontinued Code)",
        "khm": "Khmer",
        "esp": "Esperanto (Discontinued Code)",
        "epo": "Esperanto",
        "gez": "Ethiopic",
        "bho": "Bhojpuri",
        "gla": "Scottish Gaelic",
        "kas": "Kashmiri",
        "som": "Somali",
        "nai": "North American Indian (Other)",
        "fry": "Frisian",
        "crp": "Creoles and Pidgins (Other)",
        "zul": "Zulu",
        "taj": "Tajik (Discontinued Code)",
        "mao": "Maori",
        "eth": "Ethiopic (Discontinued Code)",
        "tah": "Tahitian",
        "mis": "Miscellaneous languages",
        "lan": "Occitan (post 1500) (Discontinued Code)",
        "haw": "Hawaiian",
        "sna": "Shona",
        "cpf": "Creoles and Pidgins, French-based (Other)",
        "cau": "Caucasian (Other)",
        "jrb": "Judeo-Arabic",
        "kur": "Kurdish",
        "sot": "Sotho",
        "awa": "Awadhi",
        "bre": "Breton",
        "oci": "Occitan (post-1500)",
        "ban": "Balinese",
        "ibo": "Igbo",
        "lad": "Ladino",
        "mlg": "Malagasy",
        "goh": "German, Old High (ca. 750-1050)",
        "tsn": "Tswana",
        "sux": "Sumerian",
        "ber": "Berber (Other)",
        "doi": "Dogri",
        "gua": "Guarani (Discontinued Code)",
        "bnt": "Bantu (Other)",
        "esk": "Eskimo languages (Discontinued Code)",
        "kin": "Kinyarwanda",
        "mni": "Manipuri",
        "xho": "Xhosa",
        "ssa": "Nilo-Saharan (Other)",
        "aym": "Aymara",
        "ful": "Fula",
        "dum": "Dutch, Middle (ca. 1050-1350)",
        "tar": "Tatar (Discontinued Code)"
    },
    "digitization_agent_code": {
        "google": "Google (google)",
        "ia": "Internet Archive (ia)",
        "lit-dlps-dc": "Library IT, Digital Library Production Service, Digital Conversion (lit-dlps-dc)",
        "cornell-ms": "Cornell University (with support from Microsoft) (cornell-ms)",
        "yale": "Yale University (yale)",
        "berkeley": "University of California, Berkeley (berkeley)",
        "getty": "Getty Research Institute (getty)",
        "uiuc": "University of Illinois at Urbana-Champaign (uiuc)",
        "tamu": "Texas A&M (tamu)",
        "cornell": "Cornell University (cornell)",
        "northwestern": "Northwestern University (northwestern)",
        "yale2": "Yale University (yale2)",
        "borndigital": "Born Digital (placeholder) (borndigital)",
        "nnc": "Columbia University (nnc)",
        "geu": "Emory University (geu)",
        "princeton": "Princeton University (princeton)",
        "mou": "University of Missouri-Columbia (mou)",
        "mcgill": "McGill University (mcgill)",
        "umd": "University of Maryland (umd)",
        "harvard": "Harvard University (harvard)",
        "ucsd": "University of California, San Diego (ucsd)",
        "wau": "University of Washington (wau)",
        "aub": "American University of Beirut (aub)",
        "uf": "State University System of Florida (uf)",
        "bc": "Boston College (bc)",
        "ucla": "University of California, Los Angeles (ucla)",
        "clark": "Clark Art Institute (clark)",
        "ucm": "Universidad Complutense de Madrid (ucm)",
        "upenn": "University of Pennsylvania (upenn)",
        "chtanc": "National Central Library of Taiwan (chtanc)",
        "uq": "The University of Queensland (uq)"
    },
    "format": {
        "http://id.loc.gov/ontologies/bibframe/Text": "Text",
        "http://id.loc.gov/ontologies/bibframe/NotatedMusic": "NotatedMusic",
        "http://id.loc.gov/ontologies/bibframe/Cartography": "Cartography",
        "http://id.loc.gov/ontologies/bibframe/Text http://id.loc.gov/ontologies/bibframe/Audio": "Text Audio",
        "http://id.loc.gov/ontologies/bibframe/NotatedMusic http://id.loc.gov/ontologies/bibframe/Audio": "NotatedMusic Audio",
        "http://id.loc.gov/ontologies/bibframe/MixedMaterial": "MixedMaterial",
        "http://id.loc.gov/ontologies/bibframe/StillImage": "StillImage",
        "http://id.loc.gov/ontologies/bibframe/Audio": "Audio"
    },
    "htsource": {
        "MIU": "University of Michigan (MIU)",
        "NRLF": "UC Northern Regional Library Facility (NRLF)",
        "HVD": "Harvard University (HVD)",
        "UIUC": "University of Illinois at Urbana-Champaign (UIUC)",
        "UMN": "University of Minnesota (UMN)",
        "UVA": "University of Virginia (UVA)",
        "COO": "Cornell University (COO)",
        "WU": "University of Wisconsin (WU)",
        "INU": "Indiana University (INU)",
        "UCSD": "University of California, San Diego (UCSD)",
        "TXU": "University of Texas, Austin (TXU)",
        "PST": "Pennsylvania State University (PST)",
        "NYP": "New York Public Library (NYP)",
        "OSU": "The Ohio State University (OSU)",
        "NJP": "Princeton University (NJP)",
        "UCLA": "University of California, Los Angeles (UCLA)",
        "UCSC": "University of California, Santa Cruz (UCSC)",
        "UCBK": "University of California, Berkeley (UCBK)",
        "NWU": "Northwestern University (NWU)",
        "SRLF": "UC Southern Regional Library Facility (SRLF)",
        "UCR": "University of California, Riverside (UCR)",
        "CHI": "University of Chicago (CHI)",
        "UCM": "Universidad de Complutense de Madrid (UCM)",
        "ILOC": "Library of Congress (ILOC)",
        "NNC": "Columbia University (NNC)",
        "ISRLF": "UC Southern Regional Library Facility (ISRLF)",
        "KEIO": "Keio University (KEIO)",
        "IUIUC": "University of Illinois at Urbana-Champaign (IUIUC)",
        "INRLF": "INRLF",
        "MSU": "Michigan State University (MSU)",
        "AEU": "University of Alberta (AEU)",
        "IAU": "University of Iowa (IAU)",
        "GWLA": "GWLA",
        "GRI": "GRI",
        "PUR": "Purdue University (PUR)",
        "UCD": "University of California, Davis (UCD)",
        "IUNC": "University of North Carolina at Chapel Hill (IUNC)",
        "INNC": "Columbia University (INNC)",
        "YALE": "Yale University (YALE)",
        "MU": "University of Massachusetts Amherst (MU)",
        "IDUKE": "Duke University (IDUKE)",
        "UCI": "UCI",
        "IUFL": "University of Florida (IUFL)",
        "UIUCL": "University of Illinois at Urbana-Champaign (UIUCL)",
        "IBC": "Boston College (IBC)",
        "TXCM": "Texas A&M University (TXCM)",
        "UMDB": "UMDB",
        "CTU": "University of Connecticut (CTU)",
        "IUCD": "University of California, Davis (IUCD)",
        "INCSU": "North Carolina State University (INCSU)",
        "UCSF": "University of California, San Francisco (UCSF)",
        "GEU": "Emory University (GEU)",
        "IPST": "Pennsylvania State University (IPST)",
        "MOU": "University of Missouri, Columbia (MOU)",
        "NCWSW": "Wake Forest University (NCWSW)",
        "MMET": "Tufts University (MMET)",
        "QMM": "McGill University (QMM)",
        "UCSB": "University of California, Santa Barbara (UCSB)",
        "UMLAW": "UMLAW",
        "MDU": "University of Maryland (MDU)",
        "WAU": "University of Washington (WAU)",
        "UMBUS": "UMBUS",
        "IUCLA": "University of California, Los Angeles (IUCLA)",
        "LEBAU": "American University of Beirut (LEBAU)",
        "UFDC": "University of Florida (UFDC)",
        "AZTES": "Arizona State University (AZTES)",
        "FMU": "University of Miami (FMU)",
        "MWICA": "Clark Art Institute (MWICA)",
        "PU": "University of Pennsylvania, Van Pelt-Dietrich Library (PU)",
        "AUBRU": "University of Queensland, Saint Lucia (AUBRU)"
    }
}